jardin/__init__.py
jardin/comparators.py
jardin/config.py
jardin/model.py
jardin/query.py
jardin/query_builders.py
jardin/tools.py
jardin/cache_stores/__init__.py
jardin/cache_stores/base.py
jardin/cache_stores/disk.py
jardin/cache_stores/memcached.py
jardin/cache_stores/s3.py
jardin/database/__init__.py
jardin/database/base_client.py
jardin/database/base_lexicon.py
jardin/database/client_provider.py
jardin/database/database_adapter.py
jardin/database/database_config.py
jardin/database/datasources.py
jardin/database/clients/__init__.py
jardin/database/clients/mysql.py
jardin/database/clients/pg.py
jardin/database/clients/sf.py
jardin/database/clients/sqlite.py
jardin/instrumentation/base_subscriber.py
jardin/instrumentation/event.py
jardin/instrumentation/instrumenter.py
jardin/instrumentation/notifier.py
jardin-0.22.12.dist-info/LICENSE
jardin-0.22.12.dist-info/METADATA
jardin-0.22.12.dist-info/WHEEL
jardin-0.22.12.dist-info/top_level.txt
jardin-0.22.12.dist-info/RECORD
