Metadata-Version: 2.1
Name: jardin
Version: 0.22.12
Summary: A Pandas dataframe-based ORM
Home-page: https://github.com/instacart/jardin
Author: Emmanuel Turlay
Author-email: emmanuel@instacart.com
License: MIT
Keywords: postgres mysql database ORM
Platform: UNKNOWN
Classifier: Intended Audience :: Developers
Classifier: License :: OSI Approved :: MIT License
Classifier: Programming Language :: Python :: 3
Classifier: Programming Language :: Python :: 3.5
Classifier: Programming Language :: Python :: 3.6
Classifier: Programming Language :: SQL
Classifier: Topic :: Database
Classifier: Topic :: Database :: Database Engines/Servers
Requires-Python: >=3.7, <4
Requires-Dist: pandas
Requires-Dist: numpy
Requires-Dist: psycopg2
Requires-Dist: memoized-property
Requires-Dist: inflect
Requires-Dist: future
Requires-Dist: pyarrow
Requires-Dist: boto3
Requires-Dist: snowflake-connector-python
